[
{
    "arguments": [
        "clang",
        "-c",
        "-m64",
        "-target",
        "x86_64-pc-linux-gnu",
        "-std=gnu++14",
        "-fcxx-exceptions",
        "-fexceptions",
        "-DQT_DEPRECATED_WARNINGS",
        "-DQT_QML_DEBUG",
        "-DQT_CORE_LIB",
        "-DBOOST_TYPE_INDEX_CTTI_USER_DEFINED_PARSING=(39, 1, true, \"T = \")",
        "-fPIC",
        "-I",
        "/home/gian/Uni/Pao/Qontainer/Container",
        "-I",
        "/usr/include/qt",
        "-I",
        "/usr/include/qt/QtCore",
        "-I",
        "/home/gian/Uni/Pao/build-Qontainer-Desktop-Debug/Container",
        "-I",
        "/usr/lib/qt/mkspecs/linux-g++",
        "-x",
        "c++-header",
        "/home/gian/Uni/Pao/Qontainer/Container/container.h"
    ],
    "directory": "/home/gian/Uni/Pao/build-Qontainer-Desktop-Debug",
    "file": "/home/gian/Uni/Pao/Qontainer/Container/container.h"
},
{
    "arguments": [
        "clang",
        "-c",
        "-m64",
        "-target",
        "x86_64-pc-linux-gnu",
        "-std=gnu++14",
        "-fcxx-exceptions",
        "-fexceptions",
        "-DQT_DEPRECATED_WARNINGS",
        "-DQT_QML_DEBUG",
        "-DQT_CORE_LIB",
        "-DBOOST_TYPE_INDEX_CTTI_USER_DEFINED_PARSING=(39, 1, true, \"T = \")",
        "-fPIC",
        "-I",
        "/home/gian/Uni/Pao/Qontainer/Container",
        "-I",
        "/usr/include/qt",
        "-I",
        "/usr/include/qt/QtCore",
        "-I",
        "/home/gian/Uni/Pao/build-Qontainer-Desktop-Debug/Container",
        "-I",
        "/usr/lib/qt/mkspecs/linux-g++",
        "-x",
        "c++-header",
        "/home/gian/Uni/Pao/Qontainer/Container/iterator.h"
    ],
    "directory": "/home/gian/Uni/Pao/build-Qontainer-Desktop-Debug",
    "file": "/home/gian/Uni/Pao/Qontainer/Container/iterator.h"
},
{
    "arguments": [
        "clang",
        "-c",
        "-m64",
        "-target",
        "x86_64-pc-linux-gnu",
        "-std=gnu++14",
        "-fcxx-exceptions",
        "-fexceptions",
        "-DQT_DEPRECATED_WARNINGS",
        "-DQT_QML_DEBUG",
        "-DQT_CORE_LIB",
        "-DBOOST_TYPE_INDEX_CTTI_USER_DEFINED_PARSING=(39, 1, true, \"T = \")",
        "-fPIC",
        "-I",
        "/home/gian/Uni/Pao/Qontainer/Container",
        "-I",
        "/usr/include/qt",
        "-I",
        "/usr/include/qt/QtCore",
        "-I",
        "/home/gian/Uni/Pao/build-Qontainer-Desktop-Debug/Container",
        "-I",
        "/usr/lib/qt/mkspecs/linux-g++",
        "-x",
        "c++-header",
        "/home/gian/Uni/Pao/Qontainer/Container/node.h"
    ],
    "directory": "/home/gian/Uni/Pao/build-Qontainer-Desktop-Debug",
    "file": "/home/gian/Uni/Pao/Qontainer/Container/node.h"
},
{
    "arguments": [
        "clang",
        "-c",
        "-m64",
        "-target",
        "x86_64-pc-linux-gnu",
        "-std=gnu++14",
        "-fcxx-exceptions",
        "-fexceptions",
        "-DQT_DEPRECATED_WARNINGS",
        "-DQT_QML_DEBUG",
        "-DQT_CORE_LIB",
        "-DBOOST_TYPE_INDEX_CTTI_USER_DEFINED_PARSING=(39, 1, true, \"T = \")",
        "-fPIC",
        "-I",
        "/home/gian/Uni/Pao/Qontainer/Container",
        "-I",
        "/usr/include/qt",
        "-I",
        "/usr/include/qt/QtCore",
        "-I",
        "/home/gian/Uni/Pao/build-Qontainer-Desktop-Debug/Container",
        "-I",
        "/usr/lib/qt/mkspecs/linux-g++",
        "-x",
        "objective-c++-header",
        "/home/gian/Uni/Pao/Qontainer/Container/container.h"
    ],
    "directory": "/home/gian/Uni/Pao/build-Qontainer-Desktop-Debug",
    "file": "/home/gian/Uni/Pao/Qontainer/Container/container.h"
},
{
    "arguments": [
        "clang",
        "-c",
        "-m64",
        "-target",
        "x86_64-pc-linux-gnu",
        "-std=gnu++14",
        "-fcxx-exceptions",
        "-fexceptions",
        "-DQT_DEPRECATED_WARNINGS",
        "-DQT_QML_DEBUG",
        "-DQT_CORE_LIB",
        "-DBOOST_TYPE_INDEX_CTTI_USER_DEFINED_PARSING=(39, 1, true, \"T = \")",
        "-fPIC",
        "-I",
        "/home/gian/Uni/Pao/Qontainer/Container",
        "-I",
        "/usr/include/qt",
        "-I",
        "/usr/include/qt/QtCore",
        "-I",
        "/home/gian/Uni/Pao/build-Qontainer-Desktop-Debug/Container",
        "-I",
        "/usr/lib/qt/mkspecs/linux-g++",
        "-x",
        "objective-c++-header",
        "/home/gian/Uni/Pao/Qontainer/Container/iterator.h"
    ],
    "directory": "/home/gian/Uni/Pao/build-Qontainer-Desktop-Debug",
    "file": "/home/gian/Uni/Pao/Qontainer/Container/iterator.h"
},
{
    "arguments": [
        "clang",
        "-c",
        "-m64",
        "-target",
        "x86_64-pc-linux-gnu",
        "-std=gnu++14",
        "-fcxx-exceptions",
        "-fexceptions",
        "-DQT_DEPRECATED_WARNINGS",
        "-DQT_QML_DEBUG",
        "-DQT_CORE_LIB",
        "-DBOOST_TYPE_INDEX_CTTI_USER_DEFINED_PARSING=(39, 1, true, \"T = \")",
        "-fPIC",
        "-I",
        "/home/gian/Uni/Pao/Qontainer/Container",
        "-I",
        "/usr/include/qt",
        "-I",
        "/usr/include/qt/QtCore",
        "-I",
        "/home/gian/Uni/Pao/build-Qontainer-Desktop-Debug/Container",
        "-I",
        "/usr/lib/qt/mkspecs/linux-g++",
        "-x",
        "objective-c++-header",
        "/home/gian/Uni/Pao/Qontainer/Container/node.h"
    ],
    "directory": "/home/gian/Uni/Pao/build-Qontainer-Desktop-Debug",
    "file": "/home/gian/Uni/Pao/Qontainer/Container/node.h"
},
{
    "arguments": [
        "clang",
        "-c",
        "-m64",
        "-target",
        "x86_64-pc-linux-gnu",
        "-std=gnu17",
        "-fexceptions",
        "-DQT_DEPRECATED_WARNINGS",
        "-DQT_QML_DEBUG",
        "-DQT_CORE_LIB",
        "-DBOOST_TYPE_INDEX_CTTI_USER_DEFINED_PARSING=(39, 1, true, \"T = \")",
        "-fPIC",
        "-I",
        "/home/gian/Uni/Pao/Qontainer/Container",
        "-I",
        "/usr/include/qt",
        "-I",
        "/usr/include/qt/QtCore",
        "-I",
        "/home/gian/Uni/Pao/build-Qontainer-Desktop-Debug/Container",
        "-I",
        "/usr/lib/qt/mkspecs/linux-g++",
        "-x",
        "c++-header",
        "/home/gian/Uni/Pao/Qontainer/Container/container.h"
    ],
    "directory": "/home/gian/Uni/Pao/build-Qontainer-Desktop-Debug",
    "file": "/home/gian/Uni/Pao/Qontainer/Container/container.h"
},
{
    "arguments": [
        "clang",
        "-c",
        "-m64",
        "-target",
        "x86_64-pc-linux-gnu",
        "-std=gnu17",
        "-fexceptions",
        "-DQT_DEPRECATED_WARNINGS",
        "-DQT_QML_DEBUG",
        "-DQT_CORE_LIB",
        "-DBOOST_TYPE_INDEX_CTTI_USER_DEFINED_PARSING=(39, 1, true, \"T = \")",
        "-fPIC",
        "-I",
        "/home/gian/Uni/Pao/Qontainer/Container",
        "-I",
        "/usr/include/qt",
        "-I",
        "/usr/include/qt/QtCore",
        "-I",
        "/home/gian/Uni/Pao/build-Qontainer-Desktop-Debug/Container",
        "-I",
        "/usr/lib/qt/mkspecs/linux-g++",
        "-x",
        "c++-header",
        "/home/gian/Uni/Pao/Qontainer/Container/iterator.h"
    ],
    "directory": "/home/gian/Uni/Pao/build-Qontainer-Desktop-Debug",
    "file": "/home/gian/Uni/Pao/Qontainer/Container/iterator.h"
},
{
    "arguments": [
        "clang",
        "-c",
        "-m64",
        "-target",
        "x86_64-pc-linux-gnu",
        "-std=gnu17",
        "-fexceptions",
        "-DQT_DEPRECATED_WARNINGS",
        "-DQT_QML_DEBUG",
        "-DQT_CORE_LIB",
        "-DBOOST_TYPE_INDEX_CTTI_USER_DEFINED_PARSING=(39, 1, true, \"T = \")",
        "-fPIC",
        "-I",
        "/home/gian/Uni/Pao/Qontainer/Container",
        "-I",
        "/usr/include/qt",
        "-I",
        "/usr/include/qt/QtCore",
        "-I",
        "/home/gian/Uni/Pao/build-Qontainer-Desktop-Debug/Container",
        "-I",
        "/usr/lib/qt/mkspecs/linux-g++",
        "-x",
        "c++-header",
        "/home/gian/Uni/Pao/Qontainer/Container/node.h"
    ],
    "directory": "/home/gian/Uni/Pao/build-Qontainer-Desktop-Debug",
    "file": "/home/gian/Uni/Pao/Qontainer/Container/node.h"
},
{
    "arguments": [
        "clang",
        "-c",
        "-m64",
        "-target",
        "x86_64-pc-linux-gnu",
        "-std=gnu17",
        "-fexceptions",
        "-DQT_DEPRECATED_WARNINGS",
        "-DQT_QML_DEBUG",
        "-DQT_CORE_LIB",
        "-DBOOST_TYPE_INDEX_CTTI_USER_DEFINED_PARSING=(39, 1, true, \"T = \")",
        "-fPIC",
        "-I",
        "/home/gian/Uni/Pao/Qontainer/Container",
        "-I",
        "/usr/include/qt",
        "-I",
        "/usr/include/qt/QtCore",
        "-I",
        "/home/gian/Uni/Pao/build-Qontainer-Desktop-Debug/Container",
        "-I",
        "/usr/lib/qt/mkspecs/linux-g++",
        "-x",
        "objective-c++-header",
        "/home/gian/Uni/Pao/Qontainer/Container/container.h"
    ],
    "directory": "/home/gian/Uni/Pao/build-Qontainer-Desktop-Debug",
    "file": "/home/gian/Uni/Pao/Qontainer/Container/container.h"
},
{
    "arguments": [
        "clang",
        "-c",
        "-m64",
        "-target",
        "x86_64-pc-linux-gnu",
        "-std=gnu17",
        "-fexceptions",
        "-DQT_DEPRECATED_WARNINGS",
        "-DQT_QML_DEBUG",
        "-DQT_CORE_LIB",
        "-DBOOST_TYPE_INDEX_CTTI_USER_DEFINED_PARSING=(39, 1, true, \"T = \")",
        "-fPIC",
        "-I",
        "/home/gian/Uni/Pao/Qontainer/Container",
        "-I",
        "/usr/include/qt",
        "-I",
        "/usr/include/qt/QtCore",
        "-I",
        "/home/gian/Uni/Pao/build-Qontainer-Desktop-Debug/Container",
        "-I",
        "/usr/lib/qt/mkspecs/linux-g++",
        "-x",
        "objective-c++-header",
        "/home/gian/Uni/Pao/Qontainer/Container/iterator.h"
    ],
    "directory": "/home/gian/Uni/Pao/build-Qontainer-Desktop-Debug",
    "file": "/home/gian/Uni/Pao/Qontainer/Container/iterator.h"
},
{
    "arguments": [
        "clang",
        "-c",
        "-m64",
        "-target",
        "x86_64-pc-linux-gnu",
        "-std=gnu17",
        "-fexceptions",
        "-DQT_DEPRECATED_WARNINGS",
        "-DQT_QML_DEBUG",
        "-DQT_CORE_LIB",
        "-DBOOST_TYPE_INDEX_CTTI_USER_DEFINED_PARSING=(39, 1, true, \"T = \")",
        "-fPIC",
        "-I",
        "/home/gian/Uni/Pao/Qontainer/Container",
        "-I",
        "/usr/include/qt",
        "-I",
        "/usr/include/qt/QtCore",
        "-I",
        "/home/gian/Uni/Pao/build-Qontainer-Desktop-Debug/Container",
        "-I",
        "/usr/lib/qt/mkspecs/linux-g++",
        "-x",
        "objective-c++-header",
        "/home/gian/Uni/Pao/Qontainer/Container/node.h"
    ],
    "directory": "/home/gian/Uni/Pao/build-Qontainer-Desktop-Debug",
    "file": "/home/gian/Uni/Pao/Qontainer/Container/node.h"
},
{
    "arguments": [
        "clang++",
        "-c",
        "-m64",
        "-target",
        "x86_64-pc-linux-gnu",
        "-std=gnu++14",
        "-fcxx-exceptions",
        "-fexceptions",
        "-DQT_DEPRECATED_WARNINGS",
        "-DQT_QML_DEBUG",
        "-DQT_CORE_LIB",
        "-DBOOST_TYPE_INDEX_CTTI_USER_DEFINED_PARSING=(39, 1, true, \"T = \")",
        "-fPIC",
        "-I",
        "/home/gian/Uni/Pao/Qontainer/ContainerFiller",
        "-I",
        "/home/gian/Uni/Pao/Qontainer/Container",
        "-I",
        "/home/gian/Uni/Pao/Qontainer/IoTBuilder",
        "-I",
        "/usr/include/qt",
        "-I",
        "/usr/include/qt/QtCore",
        "-I",
        "/home/gian/Uni/Pao/build-Qontainer-Desktop-Debug/ContainerFiller",
        "-I",
        "/usr/lib/qt/mkspecs/linux-g++",
        "-x",
        "c++",
        "/home/gian/Uni/Pao/Qontainer/ContainerFiller/containerfiller.cpp"
    ],
    "directory": "/home/gian/Uni/Pao/build-Qontainer-Desktop-Debug",
    "file": "/home/gian/Uni/Pao/Qontainer/ContainerFiller/containerfiller.cpp"
},
{
    "arguments": [
        "clang",
        "-c",
        "-m64",
        "-target",
        "x86_64-pc-linux-gnu",
        "-std=gnu++14",
        "-fcxx-exceptions",
        "-fexceptions",
        "-DQT_DEPRECATED_WARNINGS",
        "-DQT_QML_DEBUG",
        "-DQT_CORE_LIB",
        "-DBOOST_TYPE_INDEX_CTTI_USER_DEFINED_PARSING=(39, 1, true, \"T = \")",
        "-fPIC",
        "-I",
        "/home/gian/Uni/Pao/Qontainer/ContainerFiller",
        "-I",
        "/home/gian/Uni/Pao/Qontainer/Container",
        "-I",
        "/home/gian/Uni/Pao/Qontainer/IoTBuilder",
        "-I",
        "/usr/include/qt",
        "-I",
        "/usr/include/qt/QtCore",
        "-I",
        "/home/gian/Uni/Pao/build-Qontainer-Desktop-Debug/ContainerFiller",
        "-I",
        "/usr/lib/qt/mkspecs/linux-g++",
        "-x",
        "c++-header",
        "/home/gian/Uni/Pao/Qontainer/ContainerFiller/containerfiller.h"
    ],
    "directory": "/home/gian/Uni/Pao/build-Qontainer-Desktop-Debug",
    "file": "/home/gian/Uni/Pao/Qontainer/ContainerFiller/containerfiller.h"
},
{
    "arguments": [
        "clang++",
        "-c",
        "-m64",
        "-target",
        "x86_64-pc-linux-gnu",
        "-std=gnu++14",
        "-fcxx-exceptions",
        "-fexceptions",
        "-DQT_DEPRECATED_WARNINGS",
        "-DQT_QML_DEBUG",
        "-DQT_CORE_LIB",
        "-DBOOST_TYPE_INDEX_CTTI_USER_DEFINED_PARSING=(39, 1, true, \"T = \")",
        "-fPIC",
        "-I",
        "/home/gian/Uni/Pao/Qontainer/IoT",
        "-I",
        "/usr/include/qt",
        "-I",
        "/usr/include/qt/QtCore",
        "-I",
        "/home/gian/Uni/Pao/build-Qontainer-Desktop-Debug/IoT",
        "-I",
        "/usr/lib/qt/mkspecs/linux-g++",
        "-x",
        "c++",
        "/home/gian/Uni/Pao/Qontainer/IoT/iot.cpp"
    ],
    "directory": "/home/gian/Uni/Pao/build-Qontainer-Desktop-Debug",
    "file": "/home/gian/Uni/Pao/Qontainer/IoT/iot.cpp"
},
{
    "arguments": [
        "clang++",
        "-c",
        "-m64",
        "-target",
        "x86_64-pc-linux-gnu",
        "-std=gnu++14",
        "-fcxx-exceptions",
        "-fexceptions",
        "-DQT_DEPRECATED_WARNINGS",
        "-DQT_QML_DEBUG",
        "-DQT_CORE_LIB",
        "-DBOOST_TYPE_INDEX_CTTI_USER_DEFINED_PARSING=(39, 1, true, \"T = \")",
        "-fPIC",
        "-I",
        "/home/gian/Uni/Pao/Qontainer/IoT",
        "-I",
        "/usr/include/qt",
        "-I",
        "/usr/include/qt/QtCore",
        "-I",
        "/home/gian/Uni/Pao/build-Qontainer-Desktop-Debug/IoT",
        "-I",
        "/usr/lib/qt/mkspecs/linux-g++",
        "-x",
        "c++",
        "/home/gian/Uni/Pao/Qontainer/IoT/switch/switch.cpp"
    ],
    "directory": "/home/gian/Uni/Pao/build-Qontainer-Desktop-Debug",
    "file": "/home/gian/Uni/Pao/Qontainer/IoT/switch/switch.cpp"
},
{
    "arguments": [
        "clang++",
        "-c",
        "-m64",
        "-target",
        "x86_64-pc-linux-gnu",
        "-std=gnu++14",
        "-fcxx-exceptions",
        "-fexceptions",
        "-DQT_DEPRECATED_WARNINGS",
        "-DQT_QML_DEBUG",
        "-DQT_CORE_LIB",
        "-DBOOST_TYPE_INDEX_CTTI_USER_DEFINED_PARSING=(39, 1, true, \"T = \")",
        "-fPIC",
        "-I",
        "/home/gian/Uni/Pao/Qontainer/IoT",
        "-I",
        "/usr/include/qt",
        "-I",
        "/usr/include/qt/QtCore",
        "-I",
        "/home/gian/Uni/Pao/build-Qontainer-Desktop-Debug/IoT",
        "-I",
        "/usr/lib/qt/mkspecs/linux-g++",
        "-x",
        "c++",
        "/home/gian/Uni/Pao/Qontainer/IoT/shutter/shutter.cpp"
    ],
    "directory": "/home/gian/Uni/Pao/build-Qontainer-Desktop-Debug",
    "file": "/home/gian/Uni/Pao/Qontainer/IoT/shutter/shutter.cpp"
},
{
    "arguments": [
        "clang++",
        "-c",
        "-m64",
        "-target",
        "x86_64-pc-linux-gnu",
        "-std=gnu++14",
        "-fcxx-exceptions",
        "-fexceptions",
        "-DQT_DEPRECATED_WARNINGS",
        "-DQT_QML_DEBUG",
        "-DQT_CORE_LIB",
        "-DBOOST_TYPE_INDEX_CTTI_USER_DEFINED_PARSING=(39, 1, true, \"T = \")",
        "-fPIC",
        "-I",
        "/home/gian/Uni/Pao/Qontainer/IoT",
        "-I",
        "/usr/include/qt",
        "-I",
        "/usr/include/qt/QtCore",
        "-I",
        "/home/gian/Uni/Pao/build-Qontainer-Desktop-Debug/IoT",
        "-I",
        "/usr/lib/qt/mkspecs/linux-g++",
        "-x",
        "c++",
        "/home/gian/Uni/Pao/Qontainer/IoT/light/dimmerablelight.cpp"
    ],
    "directory": "/home/gian/Uni/Pao/build-Qontainer-Desktop-Debug",
    "file": "/home/gian/Uni/Pao/Qontainer/IoT/light/dimmerablelight.cpp"
},
{
    "arguments": [
        "clang",
        "-c",
        "-m64",
        "-target",
        "x86_64-pc-linux-gnu",
        "-std=gnu++14",
        "-fcxx-exceptions",
        "-fexceptions",
        "-DQT_DEPRECATED_WARNINGS",
        "-DQT_QML_DEBUG",
        "-DQT_CORE_LIB",
        "-DBOOST_TYPE_INDEX_CTTI_USER_DEFINED_PARSING=(39, 1, true, \"T = \")",
        "-fPIC",
        "-I",
        "/home/gian/Uni/Pao/Qontainer/IoT",
        "-I",
        "/usr/include/qt",
        "-I",
        "/usr/include/qt/QtCore",
        "-I",
        "/home/gian/Uni/Pao/build-Qontainer-Desktop-Debug/IoT",
        "-I",
        "/usr/lib/qt/mkspecs/linux-g++",
        "-x",
        "c++-header",
        "/home/gian/Uni/Pao/Qontainer/IoT/iot.h"
    ],
    "directory": "/home/gian/Uni/Pao/build-Qontainer-Desktop-Debug",
    "file": "/home/gian/Uni/Pao/Qontainer/IoT/iot.h"
},
{
    "arguments": [
        "clang",
        "-c",
        "-m64",
        "-target",
        "x86_64-pc-linux-gnu",
        "-std=gnu++14",
        "-fcxx-exceptions",
        "-fexceptions",
        "-DQT_DEPRECATED_WARNINGS",
        "-DQT_QML_DEBUG",
        "-DQT_CORE_LIB",
        "-DBOOST_TYPE_INDEX_CTTI_USER_DEFINED_PARSING=(39, 1, true, \"T = \")",
        "-fPIC",
        "-I",
        "/home/gian/Uni/Pao/Qontainer/IoT",
        "-I",
        "/usr/include/qt",
        "-I",
        "/usr/include/qt/QtCore",
        "-I",
        "/home/gian/Uni/Pao/build-Qontainer-Desktop-Debug/IoT",
        "-I",
        "/usr/lib/qt/mkspecs/linux-g++",
        "-x",
        "c++-header",
        "/home/gian/Uni/Pao/Qontainer/IoT/switch/switch.h"
    ],
    "directory": "/home/gian/Uni/Pao/build-Qontainer-Desktop-Debug",
    "file": "/home/gian/Uni/Pao/Qontainer/IoT/switch/switch.h"
},
{
    "arguments": [
        "clang",
        "-c",
        "-m64",
        "-target",
        "x86_64-pc-linux-gnu",
        "-std=gnu++14",
        "-fcxx-exceptions",
        "-fexceptions",
        "-DQT_DEPRECATED_WARNINGS",
        "-DQT_QML_DEBUG",
        "-DQT_CORE_LIB",
        "-DBOOST_TYPE_INDEX_CTTI_USER_DEFINED_PARSING=(39, 1, true, \"T = \")",
        "-fPIC",
        "-I",
        "/home/gian/Uni/Pao/Qontainer/IoT",
        "-I",
        "/usr/include/qt",
        "-I",
        "/usr/include/qt/QtCore",
        "-I",
        "/home/gian/Uni/Pao/build-Qontainer-Desktop-Debug/IoT",
        "-I",
        "/usr/lib/qt/mkspecs/linux-g++",
        "-x",
        "c++-header",
        "/home/gian/Uni/Pao/Qontainer/IoT/shutter/shutter.h"
    ],
    "directory": "/home/gian/Uni/Pao/build-Qontainer-Desktop-Debug",
    "file": "/home/gian/Uni/Pao/Qontainer/IoT/shutter/shutter.h"
},
{
    "arguments": [
        "clang",
        "-c",
        "-m64",
        "-target",
        "x86_64-pc-linux-gnu",
        "-std=gnu++14",
        "-fcxx-exceptions",
        "-fexceptions",
        "-DQT_DEPRECATED_WARNINGS",
        "-DQT_QML_DEBUG",
        "-DQT_CORE_LIB",
        "-DBOOST_TYPE_INDEX_CTTI_USER_DEFINED_PARSING=(39, 1, true, \"T = \")",
        "-fPIC",
        "-I",
        "/home/gian/Uni/Pao/Qontainer/IoT",
        "-I",
        "/usr/include/qt",
        "-I",
        "/usr/include/qt/QtCore",
        "-I",
        "/home/gian/Uni/Pao/build-Qontainer-Desktop-Debug/IoT",
        "-I",
        "/usr/lib/qt/mkspecs/linux-g++",
        "-x",
        "c++-header",
        "/home/gian/Uni/Pao/Qontainer/IoT/light/dimmerablelight.h"
    ],
    "directory": "/home/gian/Uni/Pao/build-Qontainer-Desktop-Debug",
    "file": "/home/gian/Uni/Pao/Qontainer/IoT/light/dimmerablelight.h"
},
{
    "arguments": [
        "clang++",
        "-c",
        "-m64",
        "-target",
        "x86_64-pc-linux-gnu",
        "-std=gnu++14",
        "-fcxx-exceptions",
        "-fexceptions",
        "-DQT_DEPRECATED_WARNINGS",
        "-DQT_QML_DEBUG",
        "-DQT_CORE_LIB",
        "-DBOOST_TYPE_INDEX_CTTI_USER_DEFINED_PARSING=(39, 1, true, \"T = \")",
        "-fPIC",
        "-I",
        "/home/gian/Uni/Pao/Qontainer/IoTBuilder",
        "-I",
        "/home/gian/Uni/Pao/Qontainer/IoT",
        "-I",
        "/usr/include/qt",
        "-I",
        "/usr/include/qt/QtCore",
        "-I",
        "/home/gian/Uni/Pao/build-Qontainer-Desktop-Debug/IoTBuilder",
        "-I",
        "/usr/lib/qt/mkspecs/linux-g++",
        "-x",
        "c++",
        "/home/gian/Uni/Pao/Qontainer/IoTBuilder/iotbuilder.cpp"
    ],
    "directory": "/home/gian/Uni/Pao/build-Qontainer-Desktop-Debug",
    "file": "/home/gian/Uni/Pao/Qontainer/IoTBuilder/iotbuilder.cpp"
},
{
    "arguments": [
        "clang",
        "-c",
        "-m64",
        "-target",
        "x86_64-pc-linux-gnu",
        "-std=gnu++14",
        "-fcxx-exceptions",
        "-fexceptions",
        "-DQT_DEPRECATED_WARNINGS",
        "-DQT_QML_DEBUG",
        "-DQT_CORE_LIB",
        "-DBOOST_TYPE_INDEX_CTTI_USER_DEFINED_PARSING=(39, 1, true, \"T = \")",
        "-fPIC",
        "-I",
        "/home/gian/Uni/Pao/Qontainer/IoTBuilder",
        "-I",
        "/home/gian/Uni/Pao/Qontainer/IoT",
        "-I",
        "/usr/include/qt",
        "-I",
        "/usr/include/qt/QtCore",
        "-I",
        "/home/gian/Uni/Pao/build-Qontainer-Desktop-Debug/IoTBuilder",
        "-I",
        "/usr/lib/qt/mkspecs/linux-g++",
        "-x",
        "c++-header",
        "/home/gian/Uni/Pao/Qontainer/IoTBuilder/iotbuilder.h"
    ],
    "directory": "/home/gian/Uni/Pao/build-Qontainer-Desktop-Debug",
    "file": "/home/gian/Uni/Pao/Qontainer/IoTBuilder/iotbuilder.h"
},
{
    "arguments": [
        "clang",
        "-c",
        "-m64",
        "-target",
        "x86_64-pc-linux-gnu",
        "-std=gnu++14",
        "-fcxx-exceptions",
        "-fexceptions",
        "-DQT_DEPRECATED_WARNINGS",
        "-DQT_QML_DEBUG",
        "-DQT_CORE_LIB",
        "-DBOOST_TYPE_INDEX_CTTI_USER_DEFINED_PARSING=(39, 1, true, \"T = \")",
        "-fPIC",
        "-I",
        "/home/gian/Uni/Pao/Qontainer/IoTBuilder",
        "-I",
        "/home/gian/Uni/Pao/Qontainer/IoT",
        "-I",
        "/usr/include/qt",
        "-I",
        "/usr/include/qt/QtCore",
        "-I",
        "/home/gian/Uni/Pao/build-Qontainer-Desktop-Debug/IoTBuilder",
        "-I",
        "/usr/lib/qt/mkspecs/linux-g++",
        "-x",
        "c++-header",
        "/home/gian/Uni/Pao/Qontainer/IoTBuilder/iotfactorydevice.h"
    ],
    "directory": "/home/gian/Uni/Pao/build-Qontainer-Desktop-Debug",
    "file": "/home/gian/Uni/Pao/Qontainer/IoTBuilder/iotfactorydevice.h"
},
{
    "arguments": [
        "clang",
        "-c",
        "-m64",
        "-target",
        "x86_64-pc-linux-gnu",
        "-std=gnu++14",
        "-fcxx-exceptions",
        "-fexceptions",
        "-DQT_DEPRECATED_WARNINGS",
        "-DQT_QML_DEBUG",
        "-DQT_CORE_LIB",
        "-DBOOST_TYPE_INDEX_CTTI_USER_DEFINED_PARSING=(39, 1, true, \"T = \")",
        "-fPIC",
        "-I",
        "/home/gian/Uni/Pao/Qontainer/IoTBuilder",
        "-I",
        "/home/gian/Uni/Pao/Qontainer/IoT",
        "-I",
        "/usr/include/qt",
        "-I",
        "/usr/include/qt/QtCore",
        "-I",
        "/home/gian/Uni/Pao/build-Qontainer-Desktop-Debug/IoTBuilder",
        "-I",
        "/usr/lib/qt/mkspecs/linux-g++",
        "-x",
        "c++-header",
        "/home/gian/Uni/Pao/Qontainer/IoTBuilder/iotdevices.h"
    ],
    "directory": "/home/gian/Uni/Pao/build-Qontainer-Desktop-Debug",
    "file": "/home/gian/Uni/Pao/Qontainer/IoTBuilder/iotdevices.h"
},
{
    "arguments": [
        "clang++",
        "-c",
        "-m64",
        "-target",
        "x86_64-pc-linux-gnu",
        "-std=gnu++14",
        "-fcxx-exceptions",
        "-fexceptions",
        "-DQT_TESTLIB_LIB",
        "-DQT_CORE_LIB",
        "-DQT_TESTCASE_BUILDDIR=\"/home/gian/Uni/Pao/build-Qontainer-Desktop-Debug/testContainer\"",
        "-DQT_QML_DEBUG",
        "-DBOOST_TYPE_INDEX_CTTI_USER_DEFINED_PARSING=(39, 1, true, \"T = \")",
        "-fPIC",
        "-I",
        "/home/gian/Uni/Pao/Qontainer/testContainer",
        "-I",
        "/home/gian/Uni/Pao/Qontainer/Container",
        "-I",
        "/usr/include/qt",
        "-I",
        "/usr/include/qt/QtTest",
        "-I",
        "/usr/include/qt/QtCore",
        "-I",
        "/home/gian/Uni/Pao/build-Qontainer-Desktop-Debug/testContainer",
        "-I",
        "/usr/lib/qt/mkspecs/linux-g++",
        "-x",
        "c++",
        "/home/gian/Uni/Pao/Qontainer/testContainer/tst_container.cpp"
    ],
    "directory": "/home/gian/Uni/Pao/build-Qontainer-Desktop-Debug",
    "file": "/home/gian/Uni/Pao/Qontainer/testContainer/tst_container.cpp"
},
{
    "arguments": [
        "clang++",
        "-c",
        "-m64",
        "-target",
        "x86_64-pc-linux-gnu",
        "-std=gnu++14",
        "-fcxx-exceptions",
        "-fexceptions",
        "-DQT_TESTLIB_LIB",
        "-DQT_CORE_LIB",
        "-DQT_TESTCASE_BUILDDIR=\"/home/gian/Uni/Pao/build-Qontainer-Desktop-Debug/testIoTBuilder\"",
        "-DQT_QML_DEBUG",
        "-DBOOST_TYPE_INDEX_CTTI_USER_DEFINED_PARSING=(39, 1, true, \"T = \")",
        "-fPIC",
        "-I",
        "/home/gian/Uni/Pao/Qontainer/testIoTBuilder",
        "-I",
        "/home/gian/Uni/Pao/Qontainer/IoTBuilder",
        "-I",
        "/home/gian/Uni/Pao/Qontainer/IoT",
        "-I",
        "/usr/include/qt",
        "-I",
        "/usr/include/qt/QtTest",
        "-I",
        "/usr/include/qt/QtCore",
        "-I",
        "/home/gian/Uni/Pao/build-Qontainer-Desktop-Debug/testIoTBuilder",
        "-I",
        "/usr/lib/qt/mkspecs/linux-g++",
        "-x",
        "c++",
        "/home/gian/Uni/Pao/Qontainer/testIoTBuilder/tst_test_iot_builder.cpp"
    ],
    "directory": "/home/gian/Uni/Pao/build-Qontainer-Desktop-Debug",
    "file": "/home/gian/Uni/Pao/Qontainer/testIoTBuilder/tst_test_iot_builder.cpp"
},
{
    "arguments": [
        "clang++",
        "-c",
        "-m64",
        "-target",
        "x86_64-pc-linux-gnu",
        "-std=gnu++14",
        "-fcxx-exceptions",
        "-fexceptions",
        "-DQT_TESTLIB_LIB",
        "-DQT_CORE_LIB",
        "-DQT_TESTCASE_BUILDDIR=\"/home/gian/Uni/Pao/build-Qontainer-Desktop-Debug/testLight\"",
        "-DQT_QML_DEBUG",
        "-DBOOST_TYPE_INDEX_CTTI_USER_DEFINED_PARSING=(39, 1, true, \"T = \")",
        "-fPIC",
        "-I",
        "/home/gian/Uni/Pao/Qontainer/testLight",
        "-I",
        "/home/gian/Uni/Pao/Qontainer/IoT/light",
        "-I",
        "/usr/include/qt",
        "-I",
        "/usr/include/qt/QtTest",
        "-I",
        "/usr/include/qt/QtCore",
        "-I",
        "/home/gian/Uni/Pao/build-Qontainer-Desktop-Debug/testLight",
        "-I",
        "/usr/lib/qt/mkspecs/linux-g++",
        "-x",
        "c++",
        "/home/gian/Uni/Pao/Qontainer/testLight/tst_test_light.cpp"
    ],
    "directory": "/home/gian/Uni/Pao/build-Qontainer-Desktop-Debug",
    "file": "/home/gian/Uni/Pao/Qontainer/testLight/tst_test_light.cpp"
},
{
    "arguments": [
        "clang++",
        "-c",
        "-m64",
        "-target",
        "x86_64-pc-linux-gnu",
        "-std=gnu++14",
        "-fcxx-exceptions",
        "-fexceptions",
        "-DQT_TESTLIB_LIB",
        "-DQT_CORE_LIB",
        "-DQT_TESTCASE_BUILDDIR=\"/home/gian/Uni/Pao/build-Qontainer-Desktop-Debug/testShutter\"",
        "-DQT_QML_DEBUG",
        "-DBOOST_TYPE_INDEX_CTTI_USER_DEFINED_PARSING=(39, 1, true, \"T = \")",
        "-fPIC",
        "-I",
        "/home/gian/Uni/Pao/Qontainer/testShutter",
        "-I",
        "/home/gian/Uni/Pao/Qontainer/IoT/shutter",
        "-I",
        "/usr/include/qt",
        "-I",
        "/usr/include/qt/QtTest",
        "-I",
        "/usr/include/qt/QtCore",
        "-I",
        "/home/gian/Uni/Pao/build-Qontainer-Desktop-Debug/testShutter",
        "-I",
        "/usr/lib/qt/mkspecs/linux-g++",
        "-x",
        "c++",
        "/home/gian/Uni/Pao/Qontainer/testShutter/tst_test_shutter.cpp"
    ],
    "directory": "/home/gian/Uni/Pao/build-Qontainer-Desktop-Debug",
    "file": "/home/gian/Uni/Pao/Qontainer/testShutter/tst_test_shutter.cpp"
},
{
    "arguments": [
        "clang++",
        "-c",
        "-m64",
        "-target",
        "x86_64-pc-linux-gnu",
        "-std=gnu++14",
        "-fcxx-exceptions",
        "-fexceptions",
        "-DQT_TESTLIB_LIB",
        "-DQT_CORE_LIB",
        "-DQT_TESTCASE_BUILDDIR=\"/home/gian/Uni/Pao/build-Qontainer-Desktop-Debug/testSwitch\"",
        "-DQT_QML_DEBUG",
        "-DBOOST_TYPE_INDEX_CTTI_USER_DEFINED_PARSING=(39, 1, true, \"T = \")",
        "-fPIC",
        "-I",
        "/home/gian/Uni/Pao/Qontainer/testSwitch",
        "-I",
        "/home/gian/Uni/Pao/Qontainer/IoT",
        "-I",
        "/home/gian/Uni/Pao/Qontainer/IoT/switch",
        "-I",
        "/usr/include/qt",
        "-I",
        "/usr/include/qt/QtTest",
        "-I",
        "/usr/include/qt/QtCore",
        "-I",
        "/home/gian/Uni/Pao/build-Qontainer-Desktop-Debug/testSwitch",
        "-I",
        "/usr/lib/qt/mkspecs/linux-g++",
        "-x",
        "c++",
        "/home/gian/Uni/Pao/Qontainer/testSwitch/tst_test_switch.cpp"
    ],
    "directory": "/home/gian/Uni/Pao/build-Qontainer-Desktop-Debug",
    "file": "/home/gian/Uni/Pao/Qontainer/testSwitch/tst_test_switch.cpp"
}
]